{"cameraMode":{"drawMode":0,"name":"Shaded","section":"Shading Mode"},"sceneLighting":true,"audioPlay":false,"sceneViewState":{"m_AlwaysRefresh":false,"showFog":true,"showSkybox":true,"showFlares":true,"showImageEffects":true,"showParticleSystems":true,"showVisualEffectGraphs":true,"m_FxEnabled":true},"in2DMode":false,"pivot":{"x":9.246395111083985,"y":-13.118030548095704,"z":55.618534088134769},"rotation":{"x":-0.21101558208465577,"y":-0.333412230014801,"z":0.07683663070201874,"w":-0.9156515598297119},"size":60.4322624206543,"orthographic":false}